odoo10_addon_l10n_lu_mis_reports-10.0.1.1.0-py2.7-nspkg.pth
odoo/addons/l10n_lu_mis_reports/README.rst
odoo/addons/l10n_lu_mis_reports/__init__.py
odoo/addons/l10n_lu_mis_reports/__manifest__.py
odoo/addons/l10n_lu_mis_reports/data/mis_report_abr_bs.xml
odoo/addons/l10n_lu_mis_reports/data/mis_report_abr_pl.xml
odoo/addons/l10n_lu_mis_reports/data/mis_report_bs.xml
odoo/addons/l10n_lu_mis_reports/data/mis_report_bs_2016.xml
odoo/addons/l10n_lu_mis_reports/data/mis_report_bs_2016_det.xml
odoo/addons/l10n_lu_mis_reports/data/mis_report_ca.xml
odoo/addons/l10n_lu_mis_reports/data/mis_report_pl.xml
odoo/addons/l10n_lu_mis_reports/data/mis_report_pl_2016.xml
odoo/addons/l10n_lu_mis_reports/data/mis_report_pl_2016_det.xml
odoo/addons/l10n_lu_mis_reports/data/mis_report_styles.xml
odoo/addons/l10n_lu_mis_reports/i18n/de.po
odoo/addons/l10n_lu_mis_reports/i18n/fr.po
odoo/addons/l10n_lu_mis_reports/static/description/icon.png
odoo10_addon_l10n_lu_mis_reports-10.0.1.1.0.dist-info/DESCRIPTION.rst
odoo10_addon_l10n_lu_mis_reports-10.0.1.1.0.dist-info/METADATA
odoo10_addon_l10n_lu_mis_reports-10.0.1.1.0.dist-info/RECORD
odoo10_addon_l10n_lu_mis_reports-10.0.1.1.0.dist-info/WHEEL
odoo10_addon_l10n_lu_mis_reports-10.0.1.1.0.dist-info/metadata.json
odoo10_addon_l10n_lu_mis_reports-10.0.1.1.0.dist-info/namespace_packages.txt
odoo10_addon_l10n_lu_mis_reports-10.0.1.1.0.dist-info/top_level.txt
