Metadata-Version: 2.0
Name: odoo10-addon-l10n-lu-mis-reports
Version: 10.0.1.1.0
Summary: MIS Report templates for the Luxembourg P&L and Balance Sheets
Home-page: http://acsone.eu
Author: ACSONE SA/NV,Odoo Community Association (OCA)
Author-email: support@odoo-community.org
License: AGPL-3
Platform: UNKNOWN
Classifier: Programming Language :: Python
Classifier: Framework :: Odoo
Classifier: License :: OSI Approved :: GNU Affero General Public License v3
Requires-Python: ~=2.7
Requires-Dist: odoo (<10.1dev,>=10.0)
Requires-Dist: odoo10-addon-mis-builder
